setup.py
django_tsearch2.egg-info/PKG-INFO
django_tsearch2.egg-info/SOURCES.txt
django_tsearch2.egg-info/dependency_links.txt
django_tsearch2.egg-info/not-zip-safe
django_tsearch2.egg-info/top_level.txt
tsearch2/__init__.py
tsearch2/fields.py
tsearch2/gis.py
tsearch2/models.py
tsearch2/management/__init__.py
tsearch2/management/commands/__init__.py
tsearch2/management/commands/rebuild_search_indexes.py