Metadata-Version: 1.1
Name: django-tsearch2
Version: 0.3.0
Summary: Postgresql's full text search support for Django
Home-page: http://github.com/hcarvalhoalves/django-tsearch2
Author: Henrique Carvalho Alves
Author-email: hcarvalhoalves@gmail.com
License: UNKNOWN
Platform: UNKNOWN
Classifier: Development Status :: 5 - Production/Stable
Classifier: Environment :: Web Environment
Classifier: Framework :: Django
Classifier: Intended Audience :: Developers
Classifier: License :: OSI Approved :: BSD License
Classifier: Operating System :: OS Independent
Classifier: Programming Language :: Python
Classifier: Topic :: Software Development :: Libraries :: Application Frameworks
Classifier: Topic :: Software Development :: Libraries :: Python Modules
